halfedge/__init__.py
halfedge/half_edge_constructors.py
halfedge/half_edge_elements.py
halfedge/half_edge_object.py
halfedge/half_edge_querries.py
halfedge/py.typed
halfedge/type_attrib.py
halfedge/validations.py
halfedge-0.7.0.dist-info/METADATA
halfedge-0.7.0.dist-info/WHEEL
halfedge-0.7.0.dist-info/top_level.txt
halfedge-0.7.0.dist-info/RECORD
