Metadata-Version: 2.1
Name: halfedge
Version: 0.7.0
Summary: A typical half-edge data structure with some padding
Author-email: Shay Hill <shay_public@hotmail.com>
License: MIT
Requires-Python: >=3.8
Requires-Dist: paragraphs
Provides-Extra: dev
Requires-Dist: commitizen ; extra == 'dev'
Requires-Dist: coverage ; extra == 'dev'
Requires-Dist: pre-commit ; extra == 'dev'
Requires-Dist: pylint ; extra == 'dev'
Requires-Dist: pytest ; extra == 'dev'
Requires-Dist: tox ; extra == 'dev'
